{
  "version": 3,
  "requesterUsername": "huaxel",
  "requesterAvatarIconUri": {
    "$mid": 1,
    "path": "/u/17797992",
    "scheme": "https",
    "authority": "avatars.githubusercontent.com",
    "query": "v=4"
  },
  "responderUsername": "GitHub Copilot",
  "responderAvatarIconUri": {
    "id": "copilot"
  },
  "initialLocation": "panel",
  "requests": [],
  "sessionId": "4f6aebd1-631d-4765-b37b-789491636dab",
  "creationDate": 1760219235051,
  "isImported": false,
  "lastMessageDate": 1760219235051
}